[
  {
    "ContainingType": "MessageBroker.Controllers.MessagesController",
    "Method": "PostMessage",
    "RelativePath": "api/Messages",
    "HttpMethod": "POST",
    "IsController": true,
    "Order": 0,
    "Parameters": [
      {
        "Name": "message",
        "Type": "MessageBroker.Controllers.Message",
        "IsRequired": true
      }
    ],
    "ReturnTypes": []
  },
  {
    "ContainingType": "MessageBroker.Controllers.MessagesController",
    "Method": "GetMessage",
    "RelativePath": "api/Messages",
    "HttpMethod": "GET",
    "IsController": true,
    "Order": 0,
    "Parameters": [
      {
        "Name": "producer",
        "Type": "System.String",
        "IsRequired": false
      }
    ],
    "ReturnTypes": []
  }
]